purr_geographix/assets/__init__.py
purr_geographix/assets/collect/handle_query.py
purr_geographix/assets/collect/post_process.py
purr_geographix/assets/collect/recipes/completion.py
purr_geographix/assets/collect/recipes/core.py
purr_geographix/assets/collect/recipes/dst.py
purr_geographix/assets/collect/recipes/formation.py
purr_geographix/assets/collect/recipes/ip.py
purr_geographix/assets/collect/recipes/perforation.py
purr_geographix/assets/collect/recipes/production.py
purr_geographix/assets/collect/recipes/raster_log.py
purr_geographix/assets/collect/recipes/survey.py
purr_geographix/assets/collect/recipes/vector_log.py
purr_geographix/assets/collect/recipes/well.py
purr_geographix/assets/collect/recipes/zone.py
purr_geographix/assets/collect/routes_assets.py
purr_geographix/assets/collect/sql_helper.py
purr_geographix/assets/collect/xformer.py
purr_geographix/bin/du64.exe
purr_geographix/core/__init__.py
purr_geographix/core/crud.py
purr_geographix/core/database.py
purr_geographix/core/logger.py
purr_geographix/core/models.py
purr_geographix/core/routes_settings.py
purr_geographix/core/schemas.py
purr_geographix/core/sqlanywhere.py
purr_geographix/core/util.py
purr_geographix/main.py
purr_geographix/prep/__init__.py
purr_geographix/prep/setup.py
purr_geographix/recon/__init__.py
purr_geographix/recon/epsg.py
purr_geographix/recon/recon.py
purr_geographix/recon/repo_db.py
purr_geographix/recon/repo_fs.py
purr_geographix-0.1.5.dist-info/entry_points.txt
purr_geographix-0.1.5.dist-info/LICENSE
purr_geographix-0.1.5.dist-info/METADATA
purr_geographix-0.1.5.dist-info/WHEEL
purr_geographix-0.1.5.dist-info/RECORD
