Metadata-Version: 2.1
Name: purr-geographix
Version: 0.1.5
Summary: Python API to extract JSON data from GVerse GeoGraphix projects
Author: R. Bryan Hughes
Author-email: bryan@purr.io
Requires-Python: >=3.12,<4.0
Classifier: Programming Language :: Python :: 3
Classifier: Programming Language :: Python :: 3.12
Requires-Dist: alphashape (>=1.3.1,<2.0.0)
Requires-Dist: fastapi (>=0.115.0,<0.116.0)
Requires-Dist: loguru (>=0.7.2,<0.8.0)
Requires-Dist: pandas (>=2.2.3,<3.0.0)
Requires-Dist: pyodbc (>=5.1.0,<6.0.0)
Requires-Dist: retry (>=0.9.2,<0.10.0)
Requires-Dist: sqlalchemy (>=2.0.35,<3.0.0)
Requires-Dist: types-retry (>=0.9.9.4,<0.10.0.0)
Requires-Dist: uvicorn (>=0.30.6,<0.31.0)
